{
  "collections": {
    "classic": {
      "label": "The classic Collection",
      "accent": "#cd2c2c",
      "gradientFrom": "#1a1a1a",
      "gradientTo": "#8b1a1a",
      "href": "classic.html"
    },
    "nightshade": {
      "label": "The Nightshade Collection",
      "accent": "#a87fd4",
      "gradientFrom": "#1a2851",
      "gradientTo": "#5a3d66",
      "href": "nightshade.html"
    },
    "regent": {
      "label": "The Regent Collection",
      "accent": "#2ab8be",
      "gradientFrom": "#8b5a3c",
      "gradientTo": "#2d7a7e",
      "href": "regent.html"
    }
  },
  "types": {
    "sets": {
      "label": "Full Sets"
    },
    "wrist-cuffs": {
      "label": "Wrist Cuffs"
    },
    "ankle-cuffs": {
      "label": "Ankle Cuffs"
    },
    "collars": {
      "label": "Collars"
    },
    "accessories": {
      "label": "Accessories"
    }
  },
  "products": [
    {
      "id": "classic-wrist-cuffs",
      "name": "Wrist Cuffs",
      "collection": "classic",
      "type": "wrist-cuffs",
      "price": "$135",
      "description": "Our padded leather bondage cuffs are designed for comfort and built for durability, with soft suede, neoprene padding, and heavy duty hardware for serious play.",
      "details": [
        "Outer cuff made from full-grain vegetable-tanned leather",
        "Lined with luxurious and tough Italian goatskin suede",
        "Nickel-plated solid-brass hardware",
        "Closed-cell neoprene padding that won't compress over time",
        "Double riveted and hand-stitched throughout"
      ],
      "sizing": "Available in S / M / L — sizing guide below",
      "images": [
        "data/ClassicCuffs/DSC_1446.png",
        "data/ClassicCuffs/DSC_1462.png"
      ],
      "variants": [
        { "size": "S", "stripePriceId": "price_REPLACE_WRIST_S" },
        { "size": "M", "stripePriceId": "price_REPLACE_WRIST_M" },
        { "size": "L", "stripePriceId": "price_REPLACE_WRIST_L" }
      ]
    },
    {
      "id": "classic-ankle-cuffs",
      "name": "Ankle Cuffs",
      "collection": "classic",
      "type": "ankle-cuffs",
      "price": "$145",
      "description": "No gear collection is complete without a sturdy set of ankle restraints. Our ankle cuffs are slightly longer and wider than our wrist cuffs, for a comfortable and secure fit.",
      "details": [
        "Outer cuff made from full-grain vegetable-tanned leather",
        "Lined with luxurious and tough Italian goatskin suede",
        "Nickel-plated solid-brass hardware",
        "Closed-cell neoprene padding that won't compress over time",
        "Double riveted and hand-stitched throughout"
      ],
      "sizing": "Available in S / M / L — sizing guide below",
      "images": [],
      "variants": [
        { "size": "S", "stripePriceId": "prod_U1nq52fXFk8WtU" },
        { "size": "M", "stripePriceId": "prod_U1nvv3WbiOrMl4" },
        { "size": "L", "stripePriceId": "prod_U1nwgQZL1htLne" }
      ]
    },
    {
      "id": "classic-collar",
      "name": "Collar",
      "collection": "classic",
      "type": "collars",
      "price": "$95",
      "description": "Give your sub or yourself the best, with beautifully finished full-grain leather, and a plush suede lining that feels amazing against the skin. Like all of our pieces, internal neoprene padding ensures a snug and comfortable fit even when cinched down tight.",
      "details": [
        "Outer collar made from full-grain vegetable-tanned leather",
        "Lined with luxurious and tough Italian goatskin suede",
        "Nickel-plated solid-brass hardware",
        "Closed-cell neoprene padding that won't compress over time",
        "Hand-stitched throughout"
      ],
      "sizing": "Adjustable — fits necks 11\" to 16\"",
      "images": [],
      "imageDir": "data/img/classic-collar",
      "variants": [
        { "size": "S", "stripePriceId": "price_REPLACE_COLLAR_S" },
        { "size": "M", "stripePriceId": "price_REPLACE_COLLAR_M" },
        { "size": "L", "stripePriceId": "price_REPLACE_COLLAR_L" }
      ]
    }
  ]
}